virtapi/__init__.py
virtapi/api.py
virtapi/settings.py
virtapi/utilities.py
virtapi/controller/__init__.py
virtapi/controller/domain_ctrl.py
virtapi/controller/host_ctrl.py
virtapi/controller/network_ctrl.py
virtapi/model/__init__.py
virtapi/model/host.py
virtapi/model/plan.py
virtapi/model/pool.py
virtapi/model/template.py
virtapi/resources/cloudinit-config/__init__.py
virtapi/resources/cloudinit-config/meta-data
virtapi/resources/cloudinit-config/user-data
virtapi/resources/config/__init__.py
virtapi/resources/config/hosts.yml
virtapi/resources/config/plans.yml
virtapi/resources/config/templates.yml
virtapi/resources/keys/__init__.py
virtapi/resources/keys/private.key
virtapi/resources/keys/public.key
virtapi/tests/__init__.py
virtapi-1.1.1.data/scripts/vatool
virtapi-1.1.1.dist-info/DESCRIPTION.rst
virtapi-1.1.1.dist-info/METADATA
virtapi-1.1.1.dist-info/RECORD
virtapi-1.1.1.dist-info/WHEEL
virtapi-1.1.1.dist-info/metadata.json
virtapi-1.1.1.dist-info/top_level.txt
