Metadata-Version: 2.0
Name: virtapi
Version: 1.1.1
Summary: VirtAPI is powerful libvirt/kvm wrapper with cli tool out of the box.
Home-page: http://github.com/spiperac/virtapi
Author: Strahinja Piperac
Author-email: spiperac@denkei.org
License: BSD
Platform: UNKNOWN
Requires-Dist: libvirt-python
Requires-Dist: lxml (==4.1.0)
Requires-Dist: paramiko (==2.2.1)
Requires-Dist: prettytable (==0.7.2)
Requires-Dist: pyyaml (==3.12)
Requires-Dist: requests (==2.13.0)
Requires-Dist: tqdm (==4.19.4)
Requires-Dist: xmltodict (==0.10.1)
